dbmerge/__init__.py
dbmerge/dbmerge.py
dbmerge-1.0.3.dist-info/METADATA
dbmerge-1.0.3.dist-info/WHEEL
dbmerge-1.0.3.dist-info/licenses/LICENSE
dbmerge-1.0.3.dist-info/RECORD
