Metadata-Version: 2.4
Name: dbmerge
Version: 1.0.3
Summary: DBMerge is a python library for automatic merge of table data to an SQL database with insert/update/delete(or mark).
Project-URL: Homepage, https://github.com/pavel-v-sobolev/dbmerge
Project-URL: Issues, https://github.com/pavel-v-sobolev/dbmerge/issues
Project-URL: Documentation, https://github.com/pavel-v-sobolev/dbmerge/blob/main/DOCUMENTATION.md
Project-URL: Examples, https://github.com/pavel-v-sobolev/dbmerge/blob/main/user_guide.py
Author-email: Pavel Sobolev <pavel-v-sobolev@yandex.ru>
License-Expression: MIT
License-File: LICENSE
Classifier: Operating System :: OS Independent
Classifier: Programming Language :: Python :: 3
Classifier: Programming Language :: Python :: 3.10
Classifier: Programming Language :: Python :: 3.11
Classifier: Programming Language :: Python :: 3.12
Classifier: Programming Language :: Python :: 3.13
Classifier: Programming Language :: Python :: 3.14
Requires-Python: >=3.10
Requires-Dist: alembic>=1.13.0
Requires-Dist: pandas>=2.0.1
Requires-Dist: sqlalchemy>=2.0.23
Provides-Extra: dev
Requires-Dist: build; extra == 'dev'
Requires-Dist: mariadb>=1.1.5; extra == 'dev'
Requires-Dist: psycopg2>=2.9; extra == 'dev'
Requires-Dist: pytest>=7.1.1; extra == 'dev'
Requires-Dist: twine; extra == 'dev'
